{
  "Alexandra VS Elon Musk | 31/05/2021 18:58:38": {
    "player1_id": "aad764a0-0d1e-47be-8855-6f2325625311",
    "player2_id": "533024fa-7fa8-4799-a85e-c1b00beccd2a",
    "name": "Alexandra VS Elon Musk | 31/05/2021 18:58:38",
    "creator_id": "01cb117c-3375-455a-8916-81a0027bf343",
    "winner_id": "533024fa-7fa8-4799-a85e-c1b00beccd2a",
    "created_at": "2021-05-31T18:58:38.414594",
    "turn": "PLAYER2",
    "state": "FINISHED",
    "board": {
      "row1": "BBBBBNNB",
      "row0": "NNNNNNNB",
      "row7": "NNNNNNNN",
      "row6": "NNNNNBNN",
      "row3": "NBBNNBNB",
      "row2": "BBBBNBNB",
      "row5": "NNBNBNNB",
      "row4": "NNBBNNNB"
    },
    "configuration_name": "Base"
  },
  "Alexandra VS Margaret Hamilton | 31/05/2021 18:58:44": {
    "player1_id": "aad764a0-0d1e-47be-8855-6f2325625311",
    "player2_id": "f2f69711-4b88-4ce1-aaa0-c8eca2b65e25",
    "name": "Alexandra VS Margaret Hamilton | 31/05/2021 18:58:44",
    "creator_id": "01cb117c-3375-455a-8916-81a0027bf343",
    "winner_id": "f2f69711-4b88-4ce1-aaa0-c8eca2b65e25",
    "created_at": "2021-05-31T18:58:44.314711",
    "turn": "PLAYER2",
    "state": "FINISHED",
    "board": {
      "row1": "NNBBNNNN",
      "row0": "NNNNNNNN",
      "row7": "NBBNNBBN",
      "row6": "NNNNNBBN",
      "row3": "NBNNBNNN",
      "row2": "NNBNBNNN",
      "row5": "NNNBNNBN",
      "row4": "NBNNNBNN"
    },
    "configuration_name": "Base"
  },
  "Papadopoulos VS Grace Hopper | 31/05/2021 18:59:03": {
    "player1_id": "a55d7116-9e26-41f1-a655-6dbe5068c6e4",
    "player2_id": "2fb4ac14-042e-4a97-ba30-3092061e206a",
    "name": "Papadopoulos VS Grace Hopper | 31/05/2021 18:59:03",
    "creator_id": "01cb117c-3375-455a-8916-81a0027bf343",
    "winner_id": "2fb4ac14-042e-4a97-ba30-3092061e206a",
    "created_at": "2021-05-31T18:59:03.743790",
    "turn": "PLAYER2",
    "state": "FINISHED",
    "board": {
      "row1": "NNBBNNBB",
      "row0": "NNNNNNNN",
      "row7": "BNNNNNNN",
      "row6": "BBBBNBBN",
      "row3": "BNNBNBNN",
      "row2": "NNNBNNBN",
      "row5": "BBBBBNBN",
      "row4": "BNNNNNNN"
    },
    "configuration_name": "Base"
  },
  "Alumno VS Jordi | 31/05/2021 18:59:46": {
    "player1_id": "01cb117c-3375-455a-8916-81a0027bf343",
    "player2_id": "e1a9eea4-b7cf-4fc2-9a5d-11bc36110cc0",
    "name": "Alumno VS Jordi | 31/05/2021 18:59:46",
    "creator_id": "01cb117c-3375-455a-8916-81a0027bf343",
    "winner_id": "e1a9eea4-b7cf-4fc2-9a5d-11bc36110cc0",
    "created_at": "2021-05-31T18:59:46.398448",
    "turn": "PLAYER2",
    "state": "FINISHED",
    "board": {
      "row1": "?N?N?N??",
      "row0": "BNBNBNBN",
      "row7": "NBNBNBNB",
      "row6": "N?N?????",
      "row3": "?N?NBNBN",
      "row2": "BNBNBNBN",
      "row5": "NNNNBNBN",
      "row4": "NNNNBNBN"
    },
    "configuration_name": "Collage"
  },
  "Papadopoulos VS Grace Hopper | 31/05/2021 18:59:12": {
    "player1_id": "a55d7116-9e26-41f1-a655-6dbe5068c6e4",
    "player2_id": "2fb4ac14-042e-4a97-ba30-3092061e206a",
    "name": "Papadopoulos VS Grace Hopper | 31/05/2021 18:59:12",
    "creator_id": "01cb117c-3375-455a-8916-81a0027bf343",
    "winner_id": "2fb4ac14-042e-4a97-ba30-3092061e206a",
    "created_at": "2021-05-31T18:59:12.837856",
    "turn": "PLAYER2",
    "state": "FINISHED",
    "board": {
      "row1": "BN?BB?BN",
      "row0": "NN?NB?BB",
      "row7": "NN?BN?BB",
      "row6": "BN?NN?NN",
      "row3": "BB?NN?BN",
      "row2": "??N??B??",
      "row5": "??N??N??",
      "row4": "NN?NN?NB"
    },
    "configuration_name": "Squares"
  },
  "Papadopoulos VS Elon Musk | 31/05/2021 18:59:00": {
    "player1_id": "a55d7116-9e26-41f1-a655-6dbe5068c6e4",
    "player2_id": "533024fa-7fa8-4799-a85e-c1b00beccd2a",
    "name": "Papadopoulos VS Elon Musk | 31/05/2021 18:59:00",
    "creator_id": "01cb117c-3375-455a-8916-81a0027bf343",
    "winner_id": "a55d7116-9e26-41f1-a655-6dbe5068c6e4",
    "created_at": "2021-05-31T18:59:00.225131",
    "turn": "PLAYER2",
    "state": "FINISHED",
    "board": {
      "row1": "BNNNBBNB",
      "row0": "BBBBBBNB",
      "row7": "BNNNBBBB",
      "row6": "BNNNNBBB",
      "row3": "BNBNBBNB",
      "row2": "BNNBBBNB",
      "row5": "BNBNNNBB",
      "row4": "BNBNBBNB"
    },
    "configuration_name": "Base"
  },
  "Jordi VS Grace Hopper | 31/05/2021 19:25:20": {
    "player1_id": "e1a9eea4-b7cf-4fc2-9a5d-11bc36110cc0",
    "player2_id": "2fb4ac14-042e-4a97-ba30-3092061e206a",
    "name": "Jordi VS Grace Hopper | 31/05/2021 19:25:20",
    "creator_id": "e1a9eea4-b7cf-4fc2-9a5d-11bc36110cc0",
    "winner_id": null,
    "created_at": "2021-05-31T19:25:20.370826",
    "turn": "PLAYER1",
    "state": "NOT_STARTED",
    "board": {
      "row1": "????????",
      "row0": "????????",
      "row7": "????????",
      "row6": "????????",
      "row3": "???BN???",
      "row2": "????????",
      "row5": "????????",
      "row4": "???NB???"
    },
    "configuration_name": "Base"
  },
  "Papadopoulos VS Grace Hopper | 31/05/2021 18:59:29": {
    "player1_id": "a55d7116-9e26-41f1-a655-6dbe5068c6e4",
    "player2_id": "2fb4ac14-042e-4a97-ba30-3092061e206a",
    "name": "Papadopoulos VS Grace Hopper | 31/05/2021 18:59:29",
    "creator_id": "01cb117c-3375-455a-8916-81a0027bf343",
    "winner_id": "2fb4ac14-042e-4a97-ba30-3092061e206a",
    "created_at": "2021-05-31T18:59:29.032360",
    "turn": "PLAYER2",
    "state": "FINISHED",
    "board": {
      "row1": "?NNNNNNN",
      "row0": "BNNNNNNN",
      "row7": "NNNNNNNB",
      "row6": "NNNBBBBB",
      "row3": "NNNNNNNN",
      "row2": "NNNNNNNN",
      "row5": "NBNBNBNN",
      "row4": "NNNNNNNN"
    },
    "configuration_name": "Extended"
  },
  "Margaret Hamilton VS Papadopoulos | 31/05/2021 18:59:34": {
    "player1_id": "f2f69711-4b88-4ce1-aaa0-c8eca2b65e25",
    "player2_id": "a55d7116-9e26-41f1-a655-6dbe5068c6e4",
    "name": "Margaret Hamilton VS Papadopoulos | 31/05/2021 18:59:34",
    "creator_id": "01cb117c-3375-455a-8916-81a0027bf343",
    "winner_id": "a55d7116-9e26-41f1-a655-6dbe5068c6e4",
    "created_at": "2021-05-31T18:59:34.980491",
    "turn": "PLAYER2",
    "state": "FINISHED",
    "board": {
      "row1": "?N?N???N",
      "row0": "BNBNBNBN",
      "row7": "NBNBNBNB",
      "row6": "??N?N???",
      "row3": "BN?N?NBN",
      "row2": "BNBNBNBN",
      "row5": "BNNNNNBN",
      "row4": "BNNNNNBN"
    },
    "configuration_name": "Collage"
  },
  "Margaret Hamilton VS Elon Musk | 31/05/2021 18:58:53": {
    "player1_id": "f2f69711-4b88-4ce1-aaa0-c8eca2b65e25",
    "player2_id": "533024fa-7fa8-4799-a85e-c1b00beccd2a",
    "name": "Margaret Hamilton VS Elon Musk | 31/05/2021 18:58:53",
    "creator_id": "01cb117c-3375-455a-8916-81a0027bf343",
    "winner_id": "f2f69711-4b88-4ce1-aaa0-c8eca2b65e25",
    "created_at": "2021-05-31T18:58:53.338987",
    "turn": "PLAYER1",
    "state": "FINISHED",
    "board": {
      "row1": "NNNNNNNB",
      "row0": "BBBBBBBB",
      "row7": "BBBBBBBN",
      "row6": "NNNNNBBB",
      "row3": "NBNNBBBB",
      "row2": "NNBNBBBB",
      "row5": "NNBBBNBB",
      "row4": "NBNBNBBB"
    },
    "configuration_name": "Base"
  },
  "Margaret Hamilton VS Papadopoulos | 31/05/2021 18:58:48": {
    "player1_id": "f2f69711-4b88-4ce1-aaa0-c8eca2b65e25",
    "player2_id": "a55d7116-9e26-41f1-a655-6dbe5068c6e4",
    "name": "Margaret Hamilton VS Papadopoulos | 31/05/2021 18:58:48",
    "creator_id": "01cb117c-3375-455a-8916-81a0027bf343",
    "winner_id": "f2f69711-4b88-4ce1-aaa0-c8eca2b65e25",
    "created_at": "2021-05-31T18:58:48.577152",
    "turn": "PLAYER2",
    "state": "FINISHED",
    "board": {
      "row1": "BBBBBBBN",
      "row0": "NNBBBBBB",
      "row7": "BNNNNNNN",
      "row6": "BNNBBBBN",
      "row3": "BBBNBNBN",
      "row2": "BBNBBBBN",
      "row5": "BNBNNNBN",
      "row4": "BBBBNNBN"
    },
    "configuration_name": "Base"
  },
  "Grace Hopper VS Margaret Hamilton | 31/05/2021 18:59:17": {
    "player1_id": "2fb4ac14-042e-4a97-ba30-3092061e206a",
    "player2_id": "f2f69711-4b88-4ce1-aaa0-c8eca2b65e25",
    "name": "Grace Hopper VS Margaret Hamilton | 31/05/2021 18:59:17",
    "creator_id": "01cb117c-3375-455a-8916-81a0027bf343",
    "winner_id": "2fb4ac14-042e-4a97-ba30-3092061e206a",
    "created_at": "2021-05-31T18:59:17.371926",
    "turn": "PLAYER1",
    "state": "FINISHED",
    "board": {
      "row1": "N??????B",
      "row0": "BBBBBNNN",
      "row7": "NNNBBBBB",
      "row6": "B??????N",
      "row3": "N?B??N?N",
      "row2": "?BBBBBBB",
      "row5": "BBBBBBB?",
      "row4": "N?N??B?N"
    },
    "configuration_name": "Isolated"
  },
  "Elon Musk VS Alexandra | 31/05/2021 18:59:21": {
    "player1_id": "533024fa-7fa8-4799-a85e-c1b00beccd2a",
    "player2_id": "aad764a0-0d1e-47be-8855-6f2325625311",
    "name": "Elon Musk VS Alexandra | 31/05/2021 18:59:21",
    "creator_id": "01cb117c-3375-455a-8916-81a0027bf343",
    "winner_id": null,
    "created_at": "2021-05-31T18:59:21.644819",
    "turn": "PLAYER2",
    "state": "FINISHED",
    "board": {
      "row1": "BBBBBBNN",
      "row0": "BBBBBBNB",
      "row7": "NBNNNNNN",
      "row6": "BBNNNNNN",
      "row3": "BBBBBNNN",
      "row2": "BBBBBBNN",
      "row5": "BBNNNNNN",
      "row4": "BBBNNNNN"
    },
    "configuration_name": "Draw"
  },
  "Elon Musk VS Margaret Hamilton | 31/05/2021 19:26:55": {
    "player1_id": "533024fa-7fa8-4799-a85e-c1b00beccd2a",
    "player2_id": "f2f69711-4b88-4ce1-aaa0-c8eca2b65e25",
    "name": "Elon Musk VS Margaret Hamilton | 31/05/2021 19:26:55",
    "creator_id": "e1a9eea4-b7cf-4fc2-9a5d-11bc36110cc0",
    "winner_id": null,
    "created_at": "2021-05-31T19:26:55.525568",
    "turn": "PLAYER2",
    "state": "FINISHED",
    "board": {
      "row1": "BBBBBBNN",
      "row0": "BBBBBBNB",
      "row7": "NBNNNNNN",
      "row6": "BBNNNNNN",
      "row3": "BBBBBNNN",
      "row2": "BBBBBBNN",
      "row5": "BBNNNNNN",
      "row4": "BBBNNNNN"
    },
    "configuration_name": "Draw"
  },
  "Alexandra VS Papadopoulos | 31/05/2021 18:58:41": {
    "player1_id": "aad764a0-0d1e-47be-8855-6f2325625311",
    "player2_id": "a55d7116-9e26-41f1-a655-6dbe5068c6e4",
    "name": "Alexandra VS Papadopoulos | 31/05/2021 18:58:41",
    "creator_id": "01cb117c-3375-455a-8916-81a0027bf343",
    "winner_id": "a55d7116-9e26-41f1-a655-6dbe5068c6e4",
    "created_at": "2021-05-31T18:58:41.501824",
    "turn": "PLAYER2",
    "state": "FINISHED",
    "board": {
      "row1": "BNNBNNBN",
      "row0": "NNNNNNNN",
      "row7": "NNNNNNBN",
      "row6": "NNNBNBBN",
      "row3": "NNBBBBBN",
      "row2": "NNBNNBBN",
      "row5": "NNNNBNBN",
      "row4": "NNNBNNBN"
    },
    "configuration_name": "Base"
  },
  "Margaret Hamilton VS Grace Hopper | 31/05/2021 18:58:57": {
    "player1_id": "f2f69711-4b88-4ce1-aaa0-c8eca2b65e25",
    "player2_id": "2fb4ac14-042e-4a97-ba30-3092061e206a",
    "name": "Margaret Hamilton VS Grace Hopper | 31/05/2021 18:58:57",
    "creator_id": "01cb117c-3375-455a-8916-81a0027bf343",
    "winner_id": "2fb4ac14-042e-4a97-ba30-3092061e206a",
    "created_at": "2021-05-31T18:58:57.362384",
    "turn": "PLAYER2",
    "state": "FINISHED",
    "board": {
      "row1": "NNNNNNNN",
      "row0": "BBNNNNNN",
      "row7": "NNNNNNNN",
      "row6": "NNNNNNNN",
      "row3": "NNNBNNNN",
      "row2": "NNNNNNNN",
      "row5": "NNBNNNNN",
      "row4": "NNNNNNNN"
    },
    "configuration_name": "Base"
  },
  "Jordi VS Margaret Hamilton | 31/05/2021 19:25:41": {
    "player1_id": "e1a9eea4-b7cf-4fc2-9a5d-11bc36110cc0",
    "player2_id": "f2f69711-4b88-4ce1-aaa0-c8eca2b65e25",
    "name": "Jordi VS Margaret Hamilton | 31/05/2021 19:25:41",
    "creator_id": "e1a9eea4-b7cf-4fc2-9a5d-11bc36110cc0",
    "winner_id": null,
    "created_at": "2021-05-31T19:25:41.155607",
    "turn": "PLAYER1",
    "state": "NOT_STARTED",
    "board": {
      "row1": "?B????N?",
      "row0": "B??????N",
      "row7": "N??????B",
      "row6": "?N????B?",
      "row3": "???BN???",
      "row2": "??B??N??",
      "row5": "??N??B??",
      "row4": "???NB???"
    },
    "configuration_name": "Extended"
  },
  "Elon Musk VS Grace Hopper | 31/05/2021 18:59:07": {
    "player1_id": "533024fa-7fa8-4799-a85e-c1b00beccd2a",
    "player2_id": "2fb4ac14-042e-4a97-ba30-3092061e206a",
    "name": "Elon Musk VS Grace Hopper | 31/05/2021 18:59:07",
    "creator_id": "01cb117c-3375-455a-8916-81a0027bf343",
    "winner_id": "2fb4ac14-042e-4a97-ba30-3092061e206a",
    "created_at": "2021-05-31T18:59:07.141450",
    "turn": "PLAYER1",
    "state": "FINISHED",
    "board": {
      "row1": "NBNNBBBB",
      "row0": "NNNNBBBN",
      "row7": "NNNNNNNN",
      "row6": "NBNNNBBB",
      "row3": "NNBNBBNN",
      "row2": "NNBBBNBN",
      "row5": "NNNNNNBB",
      "row4": "NBNNBBBB"
    },
    "configuration_name": "Base"
  },
  "Jordi VS Alexandra | 31/05/2021 19:25:16": {
    "player1_id": "e1a9eea4-b7cf-4fc2-9a5d-11bc36110cc0",
    "player2_id": "aad764a0-0d1e-47be-8855-6f2325625311",
    "name": "Jordi VS Alexandra | 31/05/2021 19:25:16",
    "creator_id": "e1a9eea4-b7cf-4fc2-9a5d-11bc36110cc0",
    "winner_id": null,
    "created_at": "2021-05-31T19:25:16.076789",
    "turn": "PLAYER1",
    "state": "IN_PROGRESS",
    "board": {
      "row1": "?????NN?",
      "row0": "??????N?",
      "row7": "?N??????",
      "row6": "?NN?B???",
      "row3": "???NNN??",
      "row2": "???NNBNN",
      "row5": "?NBB????",
      "row4": "??NBNB??"
    },
    "configuration_name": "Base"
  },
  "Alexandra VS Grace Hopper | 31/05/2021 19:26:37": {
    "player1_id": "aad764a0-0d1e-47be-8855-6f2325625311",
    "player2_id": "2fb4ac14-042e-4a97-ba30-3092061e206a",
    "name": "Alexandra VS Grace Hopper | 31/05/2021 19:26:37",
    "creator_id": "e1a9eea4-b7cf-4fc2-9a5d-11bc36110cc0",
    "winner_id": null,
    "created_at": "2021-05-31T19:26:37.364153",
    "turn": "PLAYER1",
    "state": "NOT_STARTED",
    "board": {
      "row1": "????????",
      "row0": "????????",
      "row7": "????????",
      "row6": "????????",
      "row3": "???BN???",
      "row2": "????????",
      "row5": "????????",
      "row4": "???NB???"
    },
    "configuration_name": "Base"
  },
  "Alexandra VS Grace Hopper | 31/05/2021 18:58:35": {
    "player1_id": "aad764a0-0d1e-47be-8855-6f2325625311",
    "player2_id": "2fb4ac14-042e-4a97-ba30-3092061e206a",
    "name": "Alexandra VS Grace Hopper | 31/05/2021 18:58:35",
    "creator_id": "01cb117c-3375-455a-8916-81a0027bf343",
    "winner_id": "2fb4ac14-042e-4a97-ba30-3092061e206a",
    "created_at": "2021-05-31T18:58:35.902915",
    "turn": "PLAYER2",
    "state": "FINISHED",
    "board": {
      "row1": "NNNBBNNN",
      "row0": "NNNNNNNN",
      "row7": "NNNNNNNN",
      "row6": "NBBBNNNN",
      "row3": "NNNNBNNN",
      "row2": "NNNNBNNN",
      "row5": "NNNNNNNN",
      "row4": "NBNBNNNN"
    },
    "configuration_name": "Base"
  },
  "Jordi VS Alumno | 31/05/2021 18:59:54": {
    "player1_id": "e1a9eea4-b7cf-4fc2-9a5d-11bc36110cc0",
    "player2_id": "01cb117c-3375-455a-8916-81a0027bf343",
    "name": "Jordi VS Alumno | 31/05/2021 18:59:54",
    "creator_id": "01cb117c-3375-455a-8916-81a0027bf343",
    "winner_id": null,
    "created_at": "2021-05-31T18:59:54.819216",
    "turn": "PLAYER1",
    "state": "NOT_STARTED",
    "board": {
      "row1": "????????",
      "row0": "????????",
      "row7": "????????",
      "row6": "????????",
      "row3": "???BN???",
      "row2": "????????",
      "row5": "????????",
      "row4": "???NB???"
    },
    "configuration_name": "Base"
  }
}
